setup.py
main/__init__.py
main/mingjun.py
mingjun_TestPypi.egg-info/PKG-INFO
mingjun_TestPypi.egg-info/SOURCES.txt
mingjun_TestPypi.egg-info/dependency_links.txt
mingjun_TestPypi.egg-info/entry_points.txt
mingjun_TestPypi.egg-info/top_level.txt