Metadata-Version: 1.0
Name: mingjun-TestPypi
Version: 0.0.1
Summary: 测试
Home-page: https://github.com/mingjunli
Author: anly.pear
Author-email: anly.pear@gmail.com
License: UNKNOWN
Platform: UNKNOWN
